{
  "id": 2,
  "event": "donation.completed",
  "created_at": "2025-08-27T15:22:15Z",
  "environment": "prod",
  "data": {
    "donation": {
      "id": 189,
      "created_at": "2025-08-27T09:45:00Z",
      "amount": 100.00,
      "currency": "CHF",
      "campaign": "Wildhunde Patenschaft",
      "purpose": "Tierpatenschaft",
      "donor": {
        "name": "Max Müller",
        "address": "Bahnhofstrasse 1",
        "city": "8001 Zürich",
        "country": "CH",
        "email": "max.mueller@example.ch"
      },
      "payment": {
        "method": "visa",
        "status": "completed"
      }
    }
  }
}
